{
  "blake3": "c76a08cebbebb199986a5c2a7f4924e69be94fa3fde916acd45f2962d10a3100",
  "bytes": 181884,
  "path": "D:\\a\\ElephantNote\\ElephantNote\\build\\out\\addons\\releases\\elephant.ai-ocr\\elephant.ai-ocr-1.0.0-windows-x86_64.enaddon",
  "id": "elephant.ai-ocr",
  "version": "1.0.0",
  "platform": "windows-x86_64",
  "runner": "process",
  "modules": 1,
  "file": "elephant.ai-ocr-1.0.0-windows-x86_64.enaddon",
  "catalogPath": "addons/ai-ocr/releases/elephant.ai-ocr-1.0.0-windows-x86_64.enaddon"
}
