{
  "blake3": "fde4cbaa89b91dc1ba76e63b9d38992378b994d0f3d58f5385c81c06c530dd6f",
  "bytes": 181886,
  "path": "D:\\a\\ElephantNote\\ElephantNote\\build\\out\\addons\\releases\\elephant.ai-ocr\\elephant.ai-ocr-1.0.0-windows-x86_64.enaddon",
  "id": "elephant.ai-ocr",
  "version": "1.0.0",
  "platform": "windows-x86_64",
  "runner": "process",
  "modules": 1,
  "file": "elephant.ai-ocr-1.0.0-windows-x86_64.enaddon",
  "catalogPath": "addons/ai-ocr/releases/elephant.ai-ocr-1.0.0-windows-x86_64.enaddon"
}
