{
  "$schema": "../gen/schemas/desktop-schema.json",
  "identifier": "default",
  "description": "Default capability for the main window.",
  "windows": ["main"],
  "permissions": [
    "core:default",
    "opener:default",
    "dialog:default",
    "fs:default",
    "notification:default",
    "window-state:default",
    "clipboard-manager:allow-write-text",
    "clipboard-manager:allow-read-text",
    {
      "identifier": "fs:scope",
      "allow": [
        { "path": "$HOME/**/*" },
        { "path": "$DOCUMENT/**/*" },
        { "path": "$DOWNLOAD/**/*" },
        { "path": "$DESKTOP/**/*" }
      ]
    }
  ]
}
